Metadata-Version: 2.1
Name: compoundinterest
Version: 0.0.1
Summary: Module of compound interest factors which includes single payment, uniform payment series, and arithmetic gradient calculations
Home-page: https://github.com/zaafirrahman/compoundinterest
Author: Zaafirrahman
Author-email: zaafir123rahman@gmail.com
License: MIT
Keywords: compoundinterest,engineeringeconomics
Platform: UNKNOWN
Classifier: Development Status :: 5 - Production/Stable
Classifier: Intended Audience :: Education
Classifier: Intended Audience :: Financial and Insurance Industry
Classifier: Operating System :: OS Independent
Classifier: License :: OSI Approved :: MIT License
Classifier: Programming Language :: Python :: 3
